kafka_broker/__init__.py
kafka_broker/base_config.ini
kafka_broker/broker_manager.py
kafka_broker/cache.py
kafka_broker/config.py
kafka_broker/consumer.py
kafka_broker/enums.py
kafka_broker/producer.py
kafka_broker/classes/__init__.py
kafka_broker/classes/cache.py
kafka_broker/classes/consumer_storage.py
kafka_broker/classes/event_object.py
kafka_broker/classes/event_router.py
kafka_broker/exceptions/__init__.py
kafka_broker/exceptions/base.py
kafka_broker/exceptions/broker.py
kafka_broker/exceptions/cache.py
kafka_broker/schemas/__init__.py
kafka_broker/schemas/log.py
kafka_broker-0.4.10.dist-info/LICENSE
kafka_broker-0.4.10.dist-info/METADATA
kafka_broker-0.4.10.dist-info/WHEEL
kafka_broker-0.4.10.dist-info/top_level.txt
kafka_broker-0.4.10.dist-info/RECORD
