Metadata-Version: 2.1
Name: kafka-broker
Version: 0.4.10
Summary: A python package implementation for the confluent kafka package. Managing producing and consuming.
Author-email: Tijmen Simons <tijmen.simons@gmail.com>, Ivar Stek <ivarstek@hotmail.nl>
Project-URL: Homepage, https://github.com/TijmenSimons/kafka-broker
Project-URL: Bug Tracker, https://github.com/TijmenSimons/kafka-broker/issues
Classifier: Programming Language :: Python :: 3
Classifier: License :: OSI Approved :: MIT License
Classifier: Operating System :: OS Independent
Requires-Python: >=3.11
License-File: LICENSE
Requires-Dist: confluent-kafka >=2.3.0
Requires-Dist: pymemcache >=4.0.0
Requires-Dist: pydantic >=2.5.3
